fino.py
fino-1.1.0.dist-info/METADATA
fino-1.1.0.dist-info/WHEEL
fino-1.1.0.dist-info/RECORD
