Metadata-Version: 2.1
Name: fino
Version: 1.1.0
Summary: Output the Finnish word for a given integer
Project-URL: Changelog, https://github.com/hugovk/fino/releases
Project-URL: Homepage, https://github.com/hugovk/fino
Project-URL: Source, https://github.com/hugovk/fino
Author: Hugo van Kemenade
Keywords: Finnish,integers,numbers,suomi
Classifier: Development Status :: 6 - Mature
Classifier: Intended Audience :: Developers
Classifier: Intended Audience :: Education
Classifier: Intended Audience :: Science/Research
Classifier: Natural Language :: English
Classifier: Natural Language :: Finnish
Classifier: Programming Language :: Python :: 3
Classifier: Programming Language :: Python :: 3 :: Only
Classifier: Programming Language :: Python :: 3.8
Classifier: Programming Language :: Python :: 3.9
Classifier: Programming Language :: Python :: 3.10
Classifier: Programming Language :: Python :: 3.11
Classifier: Programming Language :: Python :: 3.12
Classifier: Programming Language :: Python :: Implementation :: CPython
Classifier: Programming Language :: Python :: Implementation :: PyPy
Classifier: Topic :: Artistic Software
Classifier: Topic :: Scientific/Engineering :: Artificial Intelligence
Requires-Python: >=3.8
Provides-Extra: tests
Requires-Dist: pytest; extra == 'tests'
Requires-Dist: pytest-cov; extra == 'tests'
